pyproject_toml_format/__init__.py
pyproject_toml_format/__main__.py
pyproject_toml_format/_ruff.py
pyproject_toml_format/cli.py
pyproject_toml_format/py.typed
pyproject_toml_format-0.0.4.dist-info/METADATA
pyproject_toml_format-0.0.4.dist-info/WHEEL
pyproject_toml_format-0.0.4.dist-info/entry_points.txt
pyproject_toml_format-0.0.4.dist-info/licenses/LICENSE
pyproject_toml_format-0.0.4.dist-info/RECORD
