Metadata-Version: 2.4
Name: pyproject-toml-format
Version: 0.0.4
Summary: Add your description here
Project-URL: Source, https://github.com/zeevro/pyproject-toml-format
Author-email: Zeev Rotshtein <zeevro@gmail.com>
License: MIT License
License-File: LICENSE
Requires-Python: >=3.9
Requires-Dist: packaging
Requires-Dist: tomlkit
Provides-Extra: ruff
Requires-Dist: ruff; extra == 'ruff'
